checksudoku/__init__.py
checksudoku/checksudoku.py
checksudoku-0.0.1.dist-info/LICENSE
checksudoku-0.0.1.dist-info/METADATA
checksudoku-0.0.1.dist-info/WHEEL
checksudoku-0.0.1.dist-info/top_level.txt
checksudoku-0.0.1.dist-info/RECORD
